llama_index/py.typed
llama_index/vector_stores/kdbai/__init__.py
llama_index/vector_stores/kdbai/base.py
llama_index/vector_stores/kdbai/utils.py
llama_index_vector_stores_kdbai-0.6.1.dist-info/METADATA
llama_index_vector_stores_kdbai-0.6.1.dist-info/WHEEL
llama_index_vector_stores_kdbai-0.6.1.dist-info/licenses/LICENSE
llama_index_vector_stores_kdbai-0.6.1.dist-info/RECORD
